ctpy/__init__.py
ctpy/client.py
ctpy/exceptions.py
ctpy/helpers.py
ctpy/version.py
ctpy/cli/__init__.py
ctpy/cli/cli.py
ctpy/core/__init__.py
ctpy/core/pipeline.py
ctpy/core/server.py
ctpy/core/stages.py
ctpy/tests/mock.py
ctpy/tests/test_init.py
ctp_client-1.1.0.dist-info/METADATA
ctp_client-1.1.0.dist-info/WHEEL
ctp_client-1.1.0.dist-info/entry_points.txt
ctp_client-1.1.0.dist-info/licenses/LICENSE
ctp_client-1.1.0.dist-info/RECORD
