Metadata-Version: 2.4
Name: ctp-client
Version: 1.1.0
Summary: ctp-client is a Python client for [Clinical Trials Processor](https://mircwiki.rsna.org/index.php?title=MIRC_CTP).
Project-URL: CI/CD, https://gitlab.com/radiology/infrastructure/data-curation-tools/ctp-client/-/pipelines
Project-URL: Changelog, https://ctp-client.readthedocs.io/en/latest/changelog.html
Project-URL: Documentation, https://ctp-client.readthedocs.io
Project-URL: Download, https://gitlab.com/radiology/infrastructure/data-curation-tools/ctp-client/-/archive/master/ctp-client-master.zip
Project-URL: Homepage, https://gitlab.com/radiology/infrastructure/data-curation-tools/ctp-client.git
Project-URL: Issues, https://gitlab.com/radiology/infrastructure/data-curation-tools/ctp-client/-/issues
Author-email: BIGR Imaging Infrastructure Group <imaging.infrastructure@erasmusmc.nl>
License: Apache 2.0
License-File: LICENSE
Classifier: Development Status :: 4 - Beta
Classifier: Intended Audience :: Developers
Classifier: Intended Audience :: Education
Classifier: Intended Audience :: Healthcare Industry
Classifier: Intended Audience :: Information Technology
Classifier: Intended Audience :: Science/Research
Classifier: License :: OSI Approved :: Apache Software License
Classifier: Natural Language :: English
Classifier: Operating System :: OS Independent
Classifier: Programming Language :: Python :: 3 :: Only
Classifier: Programming Language :: Python :: 3.9
Classifier: Programming Language :: Python :: 3.10
Classifier: Programming Language :: Python :: 3.11
Classifier: Programming Language :: Python :: 3.12
Classifier: Programming Language :: Python :: 3.13
Classifier: Topic :: Scientific/Engineering :: Information Analysis
Classifier: Topic :: System :: Logging
Classifier: Topic :: Utilities
Requires-Python: >=3.9
Requires-Dist: beautifulsoup4==4.12.3
Requires-Dist: click-log==0.4.0
Requires-Dist: click-loglevel==0.5.1
Requires-Dist: click==8.1.3
Requires-Dist: pydantic==2.10.3
Requires-Dist: pyyaml==6.0.2
Requires-Dist: requests>=2.22.0
Requires-Dist: tabulate==0.9.0
